ingraph/__main__.py
ingraph/cli/__init__.py
ingraph/cli/cmd_cfn.py
ingraph/cli/py.typed
ingraph/engine/Grammar
ingraph/engine/__init__.py
ingraph/engine/core.py
ingraph/engine/encoder.py
ingraph/engine/importer.py
ingraph/engine/parser.py
ingraph/engine/py.typed
ingraph-0.2.1.dist-info/entry_points.txt
ingraph-0.2.1.dist-info/LICENSE
ingraph-0.2.1.dist-info/WHEEL
ingraph-0.2.1.dist-info/METADATA
ingraph-0.2.1.dist-info/RECORD
