Metadata-Version: 2.1
Name: ingraph
Version: 0.2.1
Summary: InGraph is an Infrastructure Graph DSL for AWS CloudFormation.
Home-page: https://lifa.dev/ingraph
Author: lifa.dev
Author-email: croak@lifa.dev
Requires-Python: >=3.8,<4.0
Classifier: Programming Language :: Python :: 3
Classifier: Programming Language :: Python :: 3.8
Requires-Dist: click (>=7.1.1,<8.0.0)
Requires-Dist: ingraph.aws (<1.0.0)
Requires-Dist: more-itertools (>=8.2.0,<9.0.0)
Requires-Dist: mypy (>=0.770,<0.771)
Requires-Dist: networkx (>=2.4,<3.0)
Requires-Dist: parso (>=0.6.2,<0.7.0)
Requires-Dist: ruamel.yaml (>=0.16.10,<0.17.0)
Project-URL: Repository, https://github.com/lifadev/ingraph
